fisher/__init__.py
fisher/cfisher.cpython-37m-darwin.so
fisher/tableprinter.py
fisher_modified-0.1.5.dist-info/METADATA
fisher_modified-0.1.5.dist-info/WHEEL
fisher_modified-0.1.5.dist-info/top_level.txt
fisher_modified-0.1.5.dist-info/RECORD
