Metadata-Version: 2.1
Name: fisher-modified
Version: 0.1.5
Summary: Forked from fisher (https://github.com/brentp/fishers_exact_test). Recompile it with Cython 0.29.4 to be compatible with Python 3.7.
Home-page: https://github.com/lilab-bcb/fishers_exact_test
Author: haibao tang, brent pedersen; Bo Li
Author-email: bli28@mgh.harvard.edu
License: BSD
Keywords: statistics cython
Platform: UNKNOWN
Classifier: Development Status :: 3 - Alpha
Classifier: Intended Audience :: Developers
Classifier: Intended Audience :: Science/Research
Classifier: License :: OSI Approved :: BSD License
Classifier: Operating System :: OS Independent
Classifier: Programming Language :: Python
Classifier: Topic :: Scientific/Engineering
Classifier: Programming Language :: Python :: 2
Classifier: Programming Language :: Python :: 3
Requires-Dist: numpy
